collective.abovecontenttitleportlets-1.0.0a2-py3.11-nspkg.pth
collective/abovecontenttitleportlets/__init__.py
collective/abovecontenttitleportlets/configure.zcml
collective/abovecontenttitleportlets/interfaces.py
collective/abovecontenttitleportlets/setuphandlers.py
collective/abovecontenttitleportlets/testing.py
collective/abovecontenttitleportlets/viewlet.pt
collective/abovecontenttitleportlets/viewlet.py
collective/abovecontenttitleportlets/locales/__init__.py
collective/abovecontenttitleportlets/locales/collective.abovecontentbodyportlets.pot
collective/abovecontenttitleportlets/locales/plone.pot
collective/abovecontenttitleportlets/locales/update.sh
collective/abovecontenttitleportlets/locales/en/LC_MESSAGES/plone.mo
collective/abovecontenttitleportlets/locales/en/LC_MESSAGES/plone.po
collective/abovecontenttitleportlets/locales/nl/LC_MESSAGES/collective.abovecontentbodyportlets.mo
collective/abovecontenttitleportlets/locales/nl/LC_MESSAGES/collective.abovecontentbodyportlets.po
collective/abovecontenttitleportlets/locales/nl/LC_MESSAGES/plone.mo
collective/abovecontenttitleportlets/locales/nl/LC_MESSAGES/plone.po
collective/abovecontenttitleportlets/profiles/default/browserlayer.xml
collective/abovecontenttitleportlets/profiles/default/metadata.xml
collective/abovecontenttitleportlets/profiles/default/portlets.xml
collective/abovecontenttitleportlets/profiles/uninstall/browserlayer.xml
collective/abovecontenttitleportlets/profiles/uninstall/portlets.xml
collective/abovecontenttitleportlets/tests/__init__.py
collective/abovecontenttitleportlets/tests/test_portlet_manager.py
collective/abovecontenttitleportlets/tests/test_setup.py
collective.abovecontenttitleportlets-1.0.0a2.dist-info/LICENSE.GPL
collective.abovecontenttitleportlets-1.0.0a2.dist-info/LICENSE.rst
collective.abovecontenttitleportlets-1.0.0a2.dist-info/METADATA
collective.abovecontenttitleportlets-1.0.0a2.dist-info/WHEEL
collective.abovecontenttitleportlets-1.0.0a2.dist-info/entry_points.txt
collective.abovecontenttitleportlets-1.0.0a2.dist-info/namespace_packages.txt
collective.abovecontenttitleportlets-1.0.0a2.dist-info/top_level.txt
collective.abovecontenttitleportlets-1.0.0a2.dist-info/RECORD
